<?xml version="1.0" encoding="utf-8"?><asx:abap xmlns:asx="http://www.sap.com/abapxml">
<asx:values>
<NAMETAB>
<NAMETAB>
<NAME>NAME</NAME>
<KEY>X</KEY>
<TYPE>C</TYPE>
<LENGTH>000030</LENGTH>
<DECIMALS>-1</DECIMALS>
</NAMETAB>
<NAMETAB>
<NAME>VERSION</NAME>
<KEY>X</KEY>
<TYPE>N</TYPE>
<LENGTH>000008</LENGTH>
<DECIMALS>-1</DECIMALS>
</NAMETAB>
<NAMETAB>
<NAME>PNAME</NAME>
<KEY>X</KEY>
<TYPE>C</TYPE>
<LENGTH>000030</LENGTH>
<DECIMALS>-1</DECIMALS>
</NAMETAB>
<NAMETAB>
<NAME>PTYP</NAME>
<KEY>X</KEY>
<TYPE>C</TYPE>
<LENGTH>000001</LENGTH>
<DECIMALS>-1</DECIMALS>
</NAMETAB>
<NAMETAB>
<NAME>PINDEX</NAME>
<KEY></KEY>
<TYPE>N</TYPE>
<LENGTH>000004</LENGTH>
<DECIMALS>-1</DECIMALS>
</NAMETAB>
<NAMETAB>
<NAME>PGROUP</NAME>
<KEY></KEY>
<TYPE>C</TYPE>
<LENGTH>000030</LENGTH>
<DECIMALS>-1</DECIMALS>
</NAMETAB>
<NAMETAB>
<NAME>XMLREF_TYP</NAME>
<KEY></KEY>
<TYPE>C</TYPE>
<LENGTH>000001</LENGTH>
<DECIMALS>-1</DECIMALS>
</NAMETAB>
<NAMETAB>
<NAME>PSTRUC_TYP</NAME>
<KEY></KEY>
<TYPE>C</TYPE>
<LENGTH>000001</LENGTH>
<DECIMALS>-1</DECIMALS>
</NAMETAB>
<NAMETAB>
<NAME>PENV</NAME>
<KEY></KEY>
<TYPE>C</TYPE>
<LENGTH>000001</LENGTH>
<DECIMALS>-1</DECIMALS>
</NAMETAB>
<NAMETAB>
<NAME>PREF_TYPE</NAME>
<KEY></KEY>
<TYPE>C</TYPE>
<LENGTH>000008</LENGTH>
<DECIMALS>-1</DECIMALS>
</NAMETAB>
<NAMETAB>
<NAME>PREF_NAME</NAME>
<KEY></KEY>
<TYPE>C</TYPE>
<LENGTH>000030</LENGTH>
<DECIMALS>-1</DECIMALS>
</NAMETAB>
<NAMETAB>
<NAME>PDOM</NAME>
<KEY></KEY>
<TYPE>C</TYPE>
<LENGTH>000030</LENGTH>
<DECIMALS>-1</DECIMALS>
</NAMETAB>
<NAMETAB>
<NAME>PDATTYP</NAME>
<KEY></KEY>
<TYPE>C</TYPE>
<LENGTH>000004</LENGTH>
<DECIMALS>-1</DECIMALS>
</NAMETAB>
<NAMETAB>
<NAME>PDATLEN</NAME>
<KEY></KEY>
<TYPE>N</TYPE>
<LENGTH>000004</LENGTH>
<DECIMALS>-1</DECIMALS>
</NAMETAB>
<NAMETAB>
<NAME>PINTTYP</NAME>
<KEY></KEY>
<TYPE>C</TYPE>
<LENGTH>000001</LENGTH>
<DECIMALS>-1</DECIMALS>
</NAMETAB>
<NAMETAB>
<NAME>PINTLEN</NAME>
<KEY></KEY>
<TYPE>N</TYPE>
<LENGTH>000006</LENGTH>
<DECIMALS>-1</DECIMALS>
</NAMETAB>
<NAMETAB>
<NAME>PDECIMALS</NAME>
<KEY></KEY>
<TYPE>N</TYPE>
<LENGTH>000006</LENGTH>
<DECIMALS>-1</DECIMALS>
</NAMETAB>
<NAMETAB>
<NAME>OPTIONAL</NAME>
<KEY></KEY>
<TYPE>C</TYPE>
<LENGTH>000001</LENGTH>
<DECIMALS>-1</DECIMALS>
</NAMETAB>
<NAMETAB>
<NAME>SORT_LNR</NAME>
<KEY></KEY>
<TYPE>N</TYPE>
<LENGTH>000004</LENGTH>
<DECIMALS>-1</DECIMALS>
</NAMETAB>
<NAMETAB>
<NAME>TESTSYSTEM</NAME>
<KEY></KEY>
<TYPE>C</TYPE>
<LENGTH>000030</LENGTH>
<DECIMALS>-1</DECIMALS>
</NAMETAB>
<NAMETAB>
<NAME>PREF_NAME2</NAME>
<KEY></KEY>
<TYPE>C</TYPE>
<LENGTH>000255</LENGTH>
<DECIMALS>-1</DECIMALS>
</NAMETAB>
<NAMETAB>
<NAME>ALIAS_FLAG</NAME>
<KEY></KEY>
<TYPE>C</TYPE>
<LENGTH>000001</LENGTH>
<DECIMALS>-1</DECIMALS>
</NAMETAB>
</NAMETAB>
</asx:values>
</asx:abap>